picsl_c3d.pypy39-pp73-darwin.so
picsl_c3d-1.4.4.0.dist-info/RECORD
picsl_c3d-1.4.4.0.dist-info/WHEEL
picsl_c3d-1.4.4.0.dist-info/METADATA
picsl_c3d-1.4.4.0.dist-info/licenses/LICENSE
