Metadata-Version: 2.2
Name: picsl_c3d
Version: 1.4.4.0
Summary: Convert3D family of tools from the Penn Image Computing and Science Lab (PICSL)
Author-Email: "Paul A. Yushkevich" <pyushkevich@gmail.com>
Maintainer-Email: "Paul A. Yushkevich" <pyushkevich@gmail.com>
License:                     GNU GENERAL PUBLIC LICENSE
Classifier: Development Status :: 4 - Beta
Classifier: License :: OSI Approved :: BSD License
Classifier: Programming Language :: Python :: 3 :: Only
Classifier: Programming Language :: Python :: 3.8
Classifier: Programming Language :: Python :: 3.9
Classifier: Programming Language :: Python :: 3.10
Classifier: Programming Language :: Python :: 3.11
Classifier: Programming Language :: Python :: 3.12
Classifier: Topic :: Scientific/Engineering :: Physics
Project-URL: Homepage, https://github.com/pyushkevich/c3d
Project-URL: Documentation, https://github.com/pyushkevich/c3d/blob/master/doc/c3d.md
Requires-Python: >=3.8
Requires-Dist: typing_extensions
Requires-Dist: SimpleITK
Requires-Dist: numpy
